<?xml version="1.0" encoding="ISO-8859-1" standalone="yes"?><airport name="TOS" xsi:noNamespaceSchemaLocation="/XmlFeed.xsd" xmlns:xsi="http://www.w3.org/2001/XMLSchema-instance"><flights lastUpdate="2026-07-04T14:15:54.138272Z"><flight uniqueID="2027569107"><airline>WF</airline><flight_id>WF984</flight_id><dom_int>D</dom_int><schedule_time>2026-07-04T13:00:00Z</schedule_time><arr_dep>D</arr_dep><airport>LKL</airport><gate>27</gate><status code="D" time="2026-07-04T13:01:00Z"/></flight><flight uniqueID="707728261"><airline>LH</airline><flight_id>LH879</flight_id><dom_int>S</dom_int><schedule_time>2026-07-04T13:20:00Z</schedule_time><arr_dep>D</arr_dep><airport>FRA</airport><gate>E18</gate><status code="D" time="2026-07-04T13:38:00Z"/><delayed>Y</delayed></flight><flight uniqueID="324251588"><airline>WF</airline><flight_id>WF909</flight_id><dom_int>D</dom_int><schedule_time>2026-07-04T13:30:00Z</schedule_time><arr_dep>A</arr_dep><airport>HFT</airport><status code="A" time="2026-07-04T13:16:00Z"/><belt>1</belt></flight><flight uniqueID="1286015808"><airline>DY</airline><flight_id>DY383</flight_id><dom_int>D</dom_int><schedule_time>2026-07-04T13:35:00Z</schedule_time><arr_dep>D</arr_dep><airport>OSL</airport><gate>19</gate><status code="D" time="2026-07-04T13:41:00Z"/></flight><flight uniqueID="945216005"><airline>LH</airline><flight_id>LH2458</flight_id><dom_int>S</dom_int><schedule_time>2026-07-04T13:45:00Z</schedule_time><arr_dep>A</arr_dep><airport>MUC</airport><status code="A" time="2026-07-04T13:46:30Z"/><belt>2</belt></flight><flight uniqueID="1215222642"><airline>WF</airline><flight_id>WF934</flight_id><dom_int>D</dom_int><schedule_time>2026-07-04T14:00:00Z</schedule_time><arr_dep>D</arr_dep><airport>TOS</airport><via_airport>ALF,VDS,KKN</via_airport><gate>28</gate><status code="D" time="2026-07-04T14:00:00Z"/></flight><flight uniqueID="1450768073"><airline>LH</airline><flight_id>LH2459</flight_id><dom_int>S</dom_int><schedule_time>2026-07-04T14:30:00Z</schedule_time><arr_dep>D</arr_dep><airport>MUC</airport><gate>E18</gate><status code="E" time="2026-07-04T14:37:00Z"/></flight><flight uniqueID="2092660576"><airline>WF</airline><flight_id>WF626</flight_id><dom_int>D</dom_int><schedule_time>2026-07-04T14:50:00Z</schedule_time><arr_dep>A</arr_dep><airport>BGO</airport><status code="E" time="2026-07-04T15:03:00Z"/><delayed>Y</delayed></flight><flight uniqueID="1522002663"><airline>WF</airline><flight_id>WF985</flight_id><dom_int>D</dom_int><schedule_time>2026-07-04T15:00:00Z</schedule_time><arr_dep>A</arr_dep><airport>LKL</airport><status code="E" time="2026-07-04T14:53:00Z"/></flight><flight uniqueID="1210247090"><airline>WF</airline><flight_id>WF835</flight_id><dom_int>D</dom_int><schedule_time>2026-07-04T15:15:00Z</schedule_time><arr_dep>D</arr_dep><airport>BOO</airport><via_airport>SVJ</via_airport><gate>24</gate><status code="E" time="2026-07-04T15:15:00Z"/></flight><flight uniqueID="1559546248"><airline>SK</airline><flight_id>SK7356</flight_id><dom_int>S</dom_int><schedule_time>2026-07-04T16:15:00Z</schedule_time><arr_dep>A</arr_dep><airport>CHQ</airport><status code="E" time="2026-07-04T17:07:00Z"/><delayed>Y</delayed></flight><flight uniqueID="1051601233"><airline>SK</airline><flight_id>SK4424</flight_id><dom_int>D</dom_int><schedule_time>2026-07-04T16:25:00Z</schedule_time><arr_dep>A</arr_dep><airport>OSL</airport><status code="E" time="2026-07-04T16:13:28Z"/></flight><flight uniqueID="973435983"><airline>WF</airline><flight_id>WF852</flight_id><dom_int>D</dom_int><schedule_time>2026-07-04T16:50:00Z</schedule_time><arr_dep>A</arr_dep><airport>BOO</airport><via_airport>SKN</via_airport><status code="E" time="2026-07-04T16:56:26Z"/></flight><flight uniqueID="1972631139"><airline>SK</airline><flight_id>SK4431</flight_id><dom_int>D</dom_int><schedule_time>2026-07-04T16:55:00Z</schedule_time><arr_dep>D</arr_dep><airport>OSL</airport><gate>20</gate><status code="E" time="2026-07-04T16:55:00Z"/></flight><flight uniqueID="1215231420"><airline>WF</airline><flight_id>WF934</flight_id><dom_int>D</dom_int><schedule_time>2026-07-04T17:55:00Z</schedule_time><arr_dep>A</arr_dep><airport>TOS</airport><via_airport>ALF,VDS,KKN</via_airport><status code="E" time="2026-07-04T18:02:23Z"/></flight><flight uniqueID="1145051707"><airline>A3</airline><flight_id>A34576</flight_id><dom_int>S</dom_int><schedule_time>2026-07-04T18:05:00Z</schedule_time><arr_dep>A</arr_dep><airport>CHQ</airport><status code="E" time="2026-07-04T18:30:00Z"/><delayed>Y</delayed></flight><flight uniqueID="1081543326"><airline>WF</airline><flight_id>WF628</flight_id><dom_int>D</dom_int><schedule_time>2026-07-04T18:20:00Z</schedule_time><arr_dep>A</arr_dep><airport>BGO</airport><status code="E" time="2026-07-04T18:22:34Z"/></flight><flight uniqueID="961513889"><airline>SK</airline><flight_id>SK4433</flight_id><dom_int>D</dom_int><schedule_time>2026-07-04T18:45:00Z</schedule_time><arr_dep>D</arr_dep><airport>OSL</airport><status code="E" time="2026-07-04T18:45:00Z"/></flight><flight uniqueID="639509638"><airline>A3</airline><flight_id>A34577</flight_id><dom_int>S</dom_int><schedule_time>2026-07-04T18:55:00Z</schedule_time><arr_dep>D</arr_dep><airport>CHQ</airport><status code="E" time="2026-07-04T19:45:00Z"/><delayed>Y</delayed></flight><flight uniqueID="1566283924"><airline>SK</airline><flight_id>SK4438</flight_id><dom_int>D</dom_int><schedule_time>2026-07-04T20:50:00Z</schedule_time><arr_dep>A</arr_dep><airport>OSL</airport><status code="E" time="2026-07-04T20:39:22Z"/></flight></flights></airport>